{
    "message":{"success":"success","response_code":200},
    "allSettings":{
        "id":9798,
        "username":"jainswati",
        "user_nickname":"jainswati",
        "email":"jainoct8@gmail.com",
        "email_sent_time":"1588570285",
        "document_verified":0,
        "document_name":"",
        "user_url":"",
        "created_date":"2015-05-12T15:02:57+0530",
        "facebook_profileid":"",
        "facebook_status":0,
        "google_profileid":"",
        "google_status":0,
        "user_activation_key":"",
        "account_status":0,
        "send_message":1,
        "send_request":0,
        "shortlisted":1,
        "favourate":1,
        "display_name":"Swati Jain",
        "profile_email_sent":1,
        "emailsentstatus":1,
        "emailsentstatus1":0,
        "deactivatemail":0,
        "pemail":1
        },
    "name":"jainswati",
    "getUserDetails":{"id":31030}}